{"lzOwPv7TO7R1W7sCal1rAg==":"slide1-2000x1125.png","oQ0Pjef9nNJib5X6U1DRpA==":"p1-1440x2560.png","UD0APoKWnxu3UuCod7VN4A==":"seguro_de_carro-1080x1920.png","XPGo17BGzbsH2xu7qBiaEQ==":"manicure-1080x1920.png","Sv5h/OzxHubPk1LnYSbWLg==":"manicure-1080x1920-800x1422.png","ATTJj7VVVC0yHrSTZveGlg==":"seguro-de-carro-1080x1920-800x1422.png","zBLpWA703dzyRl3QrolUcA==":"sal%C3%83o-1080x1920.png","7YDJO0fZZE/9gLsA47S+Yg==":"software-800x1422.png","o3JNlnyACBD4drt2zKsEyQ==":"fotografo-1080x1920.png","3yoZXLC2QrTRtyNCPn0vng==":"dentista-2-1080x1920.png","F9oV+8Zs2905Ysku8Gta1Q==":"a%C3%A7aiteria%20png-1080x1920.png","FzjtffF1ojvu9m5s6sCmcA==":"cart%C3%83o_lavanderia-1080x1920.png","f/bqWVESerHkNPM+Ewxosg==":"ag%C3%AAncia%20de%20viagens-1080x1920.png","LSub5tPImzs3sYSFc5NZiA==":"supermercado-1080x1920.png","2tHMjLJ2zhtJ56iKQfor8A==":"video_game-1080x1920.png","S0+0ye5rPubHePRfGC52hw==":"oficina-1080x1920.png","SqFF1X6070+jkCQ5mELefg==":"espetinho-1080x1920.png","lfL5do77R4TwGvHh0PKtsg==":"bar%202-1080x1920.png","1L1Y7f8XH41MUWfMxtMJvg==":"musico-1080x1920.png","1NdsHs2YfW72j+JhriSyCQ==":"fisioterapeuta-1080x1920.png","MWuZRCEFKbDFE37rPUs4hQ==":"130_43bjpq25v60nfn275nb6w-1024x657.jpg","BsYzoIb1mssBpbnjFlCyJA==":"130_43bjpq25v60nfn275nb6w-1024x657.jpeg","GNzFLGZ610QJ7MAeLqZlSg==":"bussinesscards-cart%C3%B5es-interativos-seu-cart%C3%83o-de-visitas-4-1024x657.png","4kWjV4PGtDuaeVGNZxir5w==":"carto-de-visita-digital-interativo-smart-card-d_nq_np_750491-mlb31582622402_072019-f-1200x1098.jpg","8zJPVU2G4/o3TNeRIN7uJg==":"cartao-de-visitas-digital-1024x512.jpg","9c2G/mjKn2n8HfH5P7JUDw==":"cartao-de-visitas-digital-1024x512.jpeg","VpRUuSqTN3wJ7En7aO9/cQ==":"cartao-de-visitas-digital-1-1024x512.jpg","t16dbGdqOG1oA88T8zhbXw==":"cartao-de-visitas-digital-1-1024x512.jpeg","945y4xD7fpPRLb3drYfHGg==":"bussinesscards-cart%C3%B5es-interativos-seu-cart%C3%83o-de-visitas-4-1024x657.png","gRm2ZxVQzf/YVNprGZnZug==":"cartao-de-visita-digital-pizza-600x815.jpg","dN9ofvmA+Tk0YUKB7IiFZg==":"e8165ce70c3d4be559034aa4d5de5f05-900x900.jpeg","hIkmCDsq2RNjgQ8dHOjPWA==":"e8165ce70c3d4be559034aa4d5de5f05-1-900x900.jpeg","quy3K2T0gt4syKcGS+c6WA==":"cartao-de-visita-digital-interativo-ilustrapix-1-650x650.jpg","rR8ZeM1vrl0+RYgl0LyCrQ==":"cardapio-min-807x675.png","UwKnF2KLr/ocdf9gues7Jg==":"background5.jpg","T58EdMpImsrCqe/a0K+1jA==":"cartao_auto_escola-1-1080x1920.png","rnjsyxHTIiT6HxmFVwCfWQ==":"g%C3%81s-1080x1920.png","1nCRSBjKW4eo15R94FVwvQ==":"laboratorio-1-1080x1920.png","YXmGhA5aWNuYEiGOb3jKeQ==":"loja%20de%20cosmetico-1080x1920.png","NFq/JVqJqAyc7N75uEvi0A==":"loja%20de%20utilidades-1080x1920.png","tLgynDhCsDEpIYY3WuOamw==":"o%20boticario-1080x1920.png","9k/tdk8nyulZwfHJiM10Rw==":"aula%20de%20viol%C3%A3o%20png-1080x1920.png","TQ7wfBdJhjtneUj4DEVN/w==":"cachorro%20quente%20png-1080x1920.png","p89SOJcQ1GbM6dK7kaLuxA==":"cartao_moveis-1-1080x1920.png","+E96yrryJlB3jb70Q9Oz6Q==":"casa%20de%20ra%C3%A7%C3%A3o-1080x1920.png","qmHnsbHvosDlk3obUxws2g==":"concerto_de_celular-1-1080x1920.png","9FEatUE4yAb0jNCdU0/IKg==":"estetica-1-1080x1920.png","QtXJiUs4dJS79IbHhn86LA==":"eudora-1-1080x1920.png","HeUJCcWQKDcHLik63c2nCg==":"loja_de_smartphone-1-1080x1920.png","0bUrrwvRJe2w8h3OtIRAtQ==":"loja_de_roupas-1-1080x1920.png","TdxGKbpLZm1sIaSijddPag==":"loja_de_suplementos-1-1080x1920.png","YZSyOnOHJGHKu8iGxq7bHg==":"pastelaria-1-1080x1920.png","Eio6XPVEfWUnoxcCtyfM5w==":"provedor%20de%20internet-1080x1920.png","8p/VIzXuebtUzhS/AYDk6g==":"psic%C3%B3loga-1080x1920.png","x0RA9GRR8nP5NBIRUqFlAQ==":"relojoaria-1-1080x1920.png","Rda8kq1XaAAuVRSOBQlgeg==":"restaurante-1-1080x1920.png","JvtsGs+gwCJ4XvxF7EAYmg==":"veterinario-1-1080x1920.png","6XKbcPrKMfLdU56Ibz6BKw==":"cart%C3%A3o_aulas%20de%20ingles-1080x1920.png","jkUKzXUGtt5fz8wpsGPW+A==":"cart%C3%83o_temperos-1080x1920.png","zc4BLUWyaKN+gqZG70DCug==":"churrascaria-1-1080x1920.png","1rt1yNyn0Ei4TXDOAO3rug==":"clinica%20medica-1080x1920.png","hKeSagIWHaQhrKqWPXNF2g==":"confeitaria-1-1080x1920.png","DbXbU88o7TzUsOuy8GefdA==":"moda%20intima-1080x1920.png","vPzQzpnANHR8+UBwd2zmMg==":"pet%20shop-1080x1920.png","ugt8PS0ZgOaLpXH38+lGxQ==":"pizza-1-1080x1920.png","8DpGNthRPXtLt05vYxhtzA==":"mary%20kay-1080x1920.png","ADErU0eepowXjp6YAVtMxA==":"seguro%20de%20carro-1080x1920.png","Zo+hRDigtH+oVaCHnB+/6g==":"artes%20marciais%20png-1080x1920.png","4R83TF8lIZewlU6d/NQMDQ==":"sorvete-3-1080x1920.png","veke9ZgaEFTeQnY8C6+QFg==":"depiladora%20png-1080x1920.png","G2Cp4kpTpymcNNTQZfc9kg==":"advocacia-1-1080x1920.png","HUB3Uy06wrxAR5zFWHQ7+g==":"coach-1-1080x1920.png","6J5Owo32LxIH9bS9NUdoyw==":"corretor%20de%20imoveis-1080x1920.png","vkRnX+vwrf8GdhBkx7xtnA==":"hotelaria-1-1080x1920.png","XnVRF3qU5JfnX6wyyJdRUw==":"loja_de_roupas_infantil-1-1080x1920.png","QG2x2K3pOogFMkJnjTQomw==":"semi_joias-1-1080x1920.png","IUWHqas4sEOYAzvPxwDv/Q==":"dj-1-1080x1920.png","9TsCoMRPthZZ9P/2QJnQgg==":"provedor_de_internet-1-1080x1920.png","YluLUkp/Qr/A/LIVQFYVFw==":"rodizio_de_pizzas-1-1080x1920.png","B6eRVEGJX2p9mAkd3vtDtw==":"auto%20pe%C3%87as-1080x1920.png","+gkW7awcZgy+vH5cLsZIsA==":"chef%20de%20cozinha-1080x1920.png","PWPpg9RdSCILYBJrSpBuJw==":"cart%C3%83o_parque_aquatico-1080x1920.png","hB+nhbNtqYa1iWu7fY3MFA==":"farmacia-1-1080x1920.png","qu1VNAQ5pIKYY6ROhvGJtw==":"funilaria-1-1080x1920.png","vzgw7EQhWMy8L0EgBkSxOw==":"revendedor_natura-1-1080x1920.png","x37XXvV2s7nW+EVIUi8juA==":"sorveteria-1-1080x1920.png","R9c0GGE8ULuGqkuUtgPDDQ==":"cursos_profissionalizantes-1-1080x1920.png","62CZdef+A4zkw/pQ1dN9Jg==":"bar-1-1080x1920.png","Sc6Jrbl4pyq8n3Tll6S7Fw==":"hamburguer-1-1080x1920.png","7VhkNa3gdtU9h7+gPfkO+g==":"casa_de_constru%C3%87%C3%83o-1080x1920.png","Ohd5D/tAgUBB5tpl0ywOEQ==":"personal_trainer-1-1080x1920.png","FOzOlJZoGnjr8/5NxJZc/w==":"20200522-4008-719x419.png","q8h+tSHq8D03M8ounI9POA==":"20200522-4009-719x419.png","LpBZcf7HnRoBNOJGGUigfw==":"cardapio-min-1-807x675.png","bE7Oxc5DeiLbf4Gia6FOHA==":"mbr-144x128.png"}